[
  {
    "name": "Cape May County-Avalon Community Hall",
    "address": "3001 Avalon Ave, Avalon, NJ 08202"
  },
  {
    "name": "Cape May County Department of Health",
    "address": "6 Moore Road DN 601, Cape May Court House"
  },
  {
    "name": "Capital Health Medical Center - Hopewell",
    "address": "1 Capital Way, Pennington, NJ 08534"
  },
  {
    "name": "Capital Health & Mercer County at CURE Arena",
    "address": "81 Hamilton Avenue, Trenton, NJ 08611"
  },
  {
    "name": "City of Elizabeth Health Department",
    "address": "418 Palmer St, Elizabeth, NJ 07202"
  },
  {
    "name": "Deborah Heart and Lung Center - Medical Office Building",
    "address": "6 Earlin Avenue, Browns Mills, NJ 08015"
  },
  {
    "name": "EAST BRUNSWICK COMMUNITY CENTER - 2",
    "address": "721 Cranbury Road, East Brunswick, NJ 08816"
  },
  {
    "name": "Epic Church International",
    "address": "2707 MAIN STREET EXTENSION, SAYREVILLE, NJ 08872"
  },
  {
    "name": "Gloucester County Health - Mega Site",
    "address": "ROWAN COLLEGE OF SOUTH JERSEY - COLLEGE CENTER 1400 TANYARD ROAD, SEWELL, NJ 08080"
  },
  {
    "name": "Henry J Austin Health Center - Site A",
    "address": "321 N. Warren Street, Trenton, NJ 08618"
  },
  {
    "name": "International High School",
    "address": "200 Grand St, Paterson, NJ 07501"
  },
  {
    "name": "Mercer County Community College Gym",
    "address": "1200 Old Trenton Road, West Windsor, NJ 08550"
  },
  {
    "name": "Middlesex County Office of Health Services",
    "address": "1 Ericsson Drive, Piscataway, NJ 08854"
  },
  {
    "name": "Middlesex County Office Of Health Services",
    "address": "457 High Street, Perth Amboy, NJ 08861"
  },
  {
    "name": "Middlesex County Vocational School - 7",
    "address": "457 High Street, Perth Amboy, NJ 08861"
  },
  {
    "name": "MONROE TOWNSHIP SENIOR CENTER - 5",
    "address": "12 HALSEY REED ROAD, MONROE TWP, NJ 08831"
  },
  {
    "name": "PRINCETON ALLIANCE CHURCH",
    "address": "20 Schalks Crossing Road, Plainsboro, NJ 08536"
  },
  {
    "name": "Raritan Valley Community College -Somerset County",
    "address": "118 Lamington Road, Branchburg, NJ 08876"
  },
  {
    "name": "Rutgers Eric B Chandler Health Center - Site A",
    "address": "277 George Street New Brunswick"
  },
  {
    "name": "SAYREVILLE FIRE ACADEMY - 6",
    "address": "1001 FIRE ACADEMY DRIVE, SAYREVILLE, NJ 08872"
  },
  {
    "name": "ST FRANCIS MEDICAL CENTER",
    "address": "601 Hamilton Ave, Trenton, NJ 08629"
  },
  {
    "name": "THE HELDRICH HOTEL AND CONFERENCE CTR - 4",
    "address": "10 LIVINGSTON AVE, NEW BRUNSWICK, NJ 08901"
  },
  {
    "name": "TRMC at the Thomas Dunn Sports Center",
    "address": "600 Pearl Street, Elizabeth, NJ 07207"
  },
  {
    "name": "Vineland DOH-Public Health Nursing",
    "address": "631 East Landis Ave, Vineland, NJ 08360"
  }
]
